authsignal/__init__.py
authsignal/client.py
authsignal/client_tests.py
authsignal/version.py
authsignal-4.1.0.dist-info/LICENSE
authsignal-4.1.0.dist-info/METADATA
authsignal-4.1.0.dist-info/WHEEL
authsignal-4.1.0.dist-info/RECORD
