Metadata-Version: 2.3
Name: authsignal
Version: 4.1.0
Summary: Authsignal Python SDK for Passwordless Step Up Authentication
License: MIT
Author: justinsoong
Author-email: justinsoong@gmail.com
Requires-Python: >=3.8,<4.0
Classifier: License :: OSI Approved :: MIT License
Classifier: Programming Language :: Python :: 3
Classifier: Programming Language :: Python :: 3.8
Classifier: Programming Language :: Python :: 3.9
Classifier: Programming Language :: Python :: 3.10
Classifier: Programming Language :: Python :: 3.11
Classifier: Programming Language :: Python :: 3.12
Classifier: Programming Language :: Python :: 3.13
Requires-Dist: pyhumps (>=3.8.0,<4.0.0)
Requires-Dist: pyjwt (>=2.8.0,<3.0.0)
Requires-Dist: requests (>=2.28.1,<3.0.0)
Project-URL: Documentation, https://docs.authsignal.com/
Project-URL: Homepage, https://www.authsignal.com/
Project-URL: Repository, https://github.com/authsignal/authsignal-python
